subtitle/spacy_test.py
subtitle/str_utils.py
subtitle/subtitle.py
subtitle/subtitle_test.py
subtitle/utils.py
subtitle/version.py
subtitle/__pycache__/str_utils.cpython-38.pyc
subtitle/__pycache__/utils.cpython-38.pyc
xmov_subtitle-0.3.3.dist-info/METADATA
xmov_subtitle-0.3.3.dist-info/WHEEL
xmov_subtitle-0.3.3.dist-info/top_level.txt
xmov_subtitle-0.3.3.dist-info/RECORD
